[{"org_name":"McWane Inc","total":"16400","pacs":"0","indivs":"16400"},{"org_name":"Parker Towing","total":"12300","pacs":"0","indivs":"12300"},{"org_name":"Drummond Co","total":"12100","pacs":"7500","indivs":"4600"},{"org_name":"Bradley, Arant et al","total":"11000","pacs":"10000","indivs":"1000"},{"org_name":"Maynard, Cooper & Gale","total":"11000","pacs":"10000","indivs":"1000"},{"org_name":"Smith's Inc","total":"11000","pacs":"0","indivs":"11000"},{"org_name":"HealthSouth Corp","total":"10600","pacs":"2500","indivs":"8100"},{"org_name":"Alabama Farmers Federation","total":"10000","pacs":"10000","indivs":"0"},{"org_name":"Alamo PAC","total":"10000","pacs":"10000","indivs":"0"},{"org_name":"American Council of Engineering Cos","total":"10000","pacs":"10000","indivs":"0"}]