[{"org_name":"Johns Hopkins University","total":"6450","pacs":"0","indivs":"6450"},{"org_name":"Merritt Properties","total":"5400","pacs":"0","indivs":"5400"},{"org_name":"Spinnaker LLC","total":"5400","pacs":"0","indivs":"5400"},{"org_name":"Emergent BioSolutions","total":"5000","pacs":"5000","indivs":"0"},{"org_name":"Exelon Corp","total":"5000","pacs":"5000","indivs":"0"},{"org_name":"Koch Industries","total":"5000","pacs":"5000","indivs":"0"},{"org_name":"Mednax Inc","total":"5000","pacs":"5000","indivs":"0"},{"org_name":"National Marine Manufacturers Assn","total":"5000","pacs":"5000","indivs":"0"},{"org_name":"Outdoor Amusement Business Assn","total":"5000","pacs":"5000","indivs":"0"},{"org_name":"Sanofi","total":"5000","pacs":"5000","indivs":"0"}]