[{"org_name":"Continental Pacific","total":"15000","pacs":"0","indivs":"15000"},{"org_name":"Veterans United Home Loans","total":"13800","pacs":"0","indivs":"13800"},{"org_name":"Neal & Co","total":"13500","pacs":"0","indivs":"13500"},{"org_name":"Southern Co","total":"12000","pacs":"10000","indivs":"2000"},{"org_name":"Baskerville-Donovan Inc","total":"10800","pacs":"0","indivs":"10800"},{"org_name":"Henry Co Homes","total":"10800","pacs":"0","indivs":"10800"},{"org_name":"Innisfive Hotels","total":"10800","pacs":"0","indivs":"10800"},{"org_name":"John S Carr & Co","total":"10800","pacs":"0","indivs":"10800"},{"org_name":"Lewis Bear Co","total":"10800","pacs":"0","indivs":"10800"},{"org_name":"Martines Corp","total":"10800","pacs":"0","indivs":"10800"}]