[{"org_name":"JStreetPAC","total":"10600","pacs":"0","indivs":"10600"},{"org_name":"Richard E Neal for Congress Cmte","total":"8000","pacs":"8000","indivs":"0"},{"org_name":"Eversource Energy","total":"6000","pacs":"6000","indivs":"0"},{"org_name":"Arabella Insurance","total":"5400","pacs":"0","indivs":"5400"},{"org_name":"Barbara Lee Family Foundation","total":"5400","pacs":"0","indivs":"5400"},{"org_name":"Barnstable Broadcasting","total":"5400","pacs":"0","indivs":"5400"},{"org_name":"Beacon Health Strategies","total":"5400","pacs":"0","indivs":"5400"},{"org_name":"Davis Robinson & White","total":"5400","pacs":"0","indivs":"5400"},{"org_name":"Dentaquest","total":"5400","pacs":"0","indivs":"5400"},{"org_name":"Diamond Castle Holdings","total":"5400","pacs":"0","indivs":"5400"}]