[{"org_name":"Freedomworks Pac","total":"21034","pacs":"0","indivs":"21034"},{"org_name":"Tennessee Industrial Electronics","total":"10800","pacs":"0","indivs":"10800"},{"org_name":"Bachman Group","total":"5400","pacs":"0","indivs":"5400"},{"org_name":"College Loan Corp","total":"5400","pacs":"0","indivs":"5400"},{"org_name":"Covington & Burling","total":"5000","pacs":"5000","indivs":"0"},{"org_name":"DirecTV","total":"5000","pacs":"5000","indivs":"0"},{"org_name":"Qualcomm Inc","total":"5000","pacs":"5000","indivs":"0"},{"org_name":"Senate Conservatives Fund","total":"5000","pacs":"5000","indivs":"0"},{"org_name":"National Rural Electric Cooperative Assn","total":"4500","pacs":"4500","indivs":"0"},{"org_name":"Pcpi Manufacturing","total":"2700","pacs":"0","indivs":"2700"}]